braintree/__init__.py
braintree/account_updater_daily_report.py
braintree/ach_mandate.py
braintree/add_on.py
braintree/add_on_gateway.py
braintree/address.py
braintree/address_gateway.py
braintree/amex_express_checkout_card.py
braintree/android_pay_card.py
braintree/apple_pay_card.py
braintree/apple_pay_gateway.py
braintree/apple_pay_options.py
braintree/attribute_getter.py
braintree/authorization_adjustment.py
braintree/bank_account_instant_verification_gateway.py
braintree/bank_account_instant_verification_jwt.py
braintree/bank_account_instant_verification_jwt_request.py
braintree/bin_data.py
braintree/blik_alias.py
braintree/braintree_gateway.py
braintree/client_token.py
braintree/client_token_gateway.py
braintree/configuration.py
braintree/connected_merchant_paypal_status_changed.py
braintree/connected_merchant_status_transitioned.py
braintree/credentials_parser.py
braintree/credit_card.py
braintree/credit_card_gateway.py
braintree/credit_card_verification.py
braintree/credit_card_verification_gateway.py
braintree/credit_card_verification_search.py
braintree/customer.py
braintree/customer_gateway.py
braintree/customer_search.py
braintree/customer_session_gateway.py
braintree/descriptor.py
braintree/disbursement.py
braintree/disbursement_detail.py
braintree/discount.py
braintree/discount_gateway.py
braintree/dispute.py
braintree/dispute_gateway.py
braintree/dispute_search.py
braintree/document_upload.py
braintree/document_upload_gateway.py
braintree/enriched_customer_data.py
braintree/environment.py
braintree/error_codes.py
braintree/error_result.py
braintree/errors.py
braintree/europe_bank_account.py
braintree/exchange_rate_quote.py
braintree/exchange_rate_quote_gateway.py
braintree/exchange_rate_quote_input.py
braintree/exchange_rate_quote_payload.py
braintree/exchange_rate_quote_request.py
braintree/facilitated_details.py
braintree/facilitator_details.py
braintree/granted_payment_instrument_update.py
braintree/iban_bank_account.py
braintree/ids_search.py
braintree-4.41.0.dist-info/LICENSE
braintree-4.41.0.dist-info/METADATA
braintree-4.41.0.dist-info/WHEEL
braintree-4.41.0.dist-info/top_level.txt
braintree-4.41.0.dist-info/RECORD
