Metadata-Version: 2.1
Name: braintree
Version: 4.41.0
Summary: Braintree Python Library
Home-page: https://developer.paypal.com/braintree/docs/reference/overview
Author: Braintree
Author-email: support@braintreepayments.com
License: MIT
Platform: UNKNOWN
Classifier: License :: OSI Approved :: MIT License
Classifier: Programming Language :: Python :: 3.5
Classifier: Programming Language :: Python :: 3.6
Classifier: Programming Language :: Python :: 3.7
Classifier: Programming Language :: Python :: 3.8
Classifier: Programming Language :: Python :: 3.9
Classifier: Programming Language :: Python :: 3.10
Classifier: Programming Language :: Python :: 3.11
Classifier: Programming Language :: Python :: 3.12
Requires-Dist: requests (<3.0,>=0.11.1)
